geventwebsocket/__init__.py
geventwebsocket/exceptions.py
geventwebsocket/handler.py
geventwebsocket/logging.py
geventwebsocket/resource.py
geventwebsocket/server.py
geventwebsocket/utf8validator.py
geventwebsocket/utils.py
geventwebsocket/websocket.py
geventwebsocket/gunicorn/__init__.py
geventwebsocket/gunicorn/workers.py
geventwebsocket/protocols/__init__.py
geventwebsocket/protocols/base.py
geventwebsocket/protocols/wamp.py
karellen_geventws-1.0.2.dist-info/DESCRIPTION.rst
karellen_geventws-1.0.2.dist-info/METADATA
karellen_geventws-1.0.2.dist-info/RECORD
karellen_geventws-1.0.2.dist-info/WHEEL
karellen_geventws-1.0.2.dist-info/metadata.json
karellen_geventws-1.0.2.dist-info/namespace_packages.txt
karellen_geventws-1.0.2.dist-info/top_level.txt
karellen_geventws-1.0.2.dist-info/zip-safe
