Metadata-Version: 2.0
Name: karellen-geventws
Version: 1.0.2
Summary: Karellen Gevent Websocket Library
Home-page: https://github.com/karellen/karellen-geventws
Author: Jeffrey Gelens, Karellen, Inc
Author-email: jeffrey@noppo.pro, supervisor@karellen.co
License: Apache License, Version 2.0
Platform: UNKNOWN
Classifier: Development Status :: 5 - Production/Stable
Classifier: Environment :: Console
Classifier: Intended Audience :: Developers
Classifier: License :: OSI Approved :: Apache Software License
Classifier: Programming Language :: Python
Classifier: Programming Language :: Python :: 3.6
Classifier: Programming Language :: Python :: 3.3
Classifier: Programming Language :: Python :: 3.4
Classifier: Programming Language :: Python :: 3.6
Classifier: Topic :: Software Development :: Libraries
Classifier: Topic :: Software Development :: Libraries :: Python Modules
Classifier: Topic :: Internet
Requires-Python: <3.7,>=3.3
Requires-Dist: gevent
